asynctkinter/__init__.py
asynctkinter/_tkinter_stuffs.py
asynctkinter-0.4.3.dist-info/LICENSE
asynctkinter-0.4.3.dist-info/METADATA
asynctkinter-0.4.3.dist-info/WHEEL
asynctkinter-0.4.3.dist-info/RECORD
