Metadata-Version: 2.3
Name: asynctkinter
Version: 0.4.3
Summary: async library for tkinter
License: MIT
Keywords: async,tkinter
Author: Nattōsai Mitō
Author-email: flow4re2c@gmail.com
Requires-Python: >=3.10.0,<4.0.0
Classifier: Development Status :: 5 - Production/Stable
Classifier: Intended Audience :: Developers
Classifier: License :: OSI Approved :: MIT License
Classifier: Operating System :: OS Independent
Classifier: Programming Language :: Python
Classifier: Programming Language :: Python :: 3
Classifier: Programming Language :: Python :: 3.10
Classifier: Programming Language :: Python :: 3.11
Classifier: Programming Language :: Python :: 3.12
Classifier: Programming Language :: Python :: 3.13
Classifier: Topic :: Software Development :: Libraries
Requires-Dist: asyncgui (>=0.9,<0.10)
Requires-Dist: asyncgui-ext-clock (>=0.6.1,<0.7)
Project-URL: Homepage, https://github.com/gottadiveintopython/asynctkinter
Project-URL: Repository, https://github.com/gottadiveintopython/asynctkinter
